{
    "Account": "1.3.27",
    "Base": "1.3.27",
    "Bill": "1.3.27",
    "Calendar": "1.3.27",
    "Core": "1.3.27",
    "Crm": "1.3.27",
    "Discussion": "1.3.27",
    "Expense": "1.3.27",
    "Fleet": "1.3.27",
    "Hrm": "1.3.27",
    "Isp": "1.3.27",
    "Kopokopo": "1.3.27",
    "Mail": "1.3.27",
    "Mailmass": "1.3.27",
    "Media": "1.3.27",
    "Mpesa": "1.3.27",
    "Mrp": "1.3.27",
    "Partner": "1.3.27",
    "Product": "1.3.27",
    "Realestate": "1.3.27",
    "Sale": "1.3.27",
    "Sms": "1.3.27",
    "Smsmass": "1.3.27",
    "Smsreader": "1.3.27"
}